libavi/__init__.py
libavi/a1module.py
libavi/a2module.py
libavi/a3module.py
libavi-0.0.1.dist-info/LICENSE.md
libavi-0.0.1.dist-info/METADATA
libavi-0.0.1.dist-info/WHEEL
libavi-0.0.1.dist-info/top_level.txt
libavi-0.0.1.dist-info/RECORD
