Metadata-Version: 2.1
Name: libavi
Version: 0.0.1
Summary: libavi
Author: libavi
Author-email: xeetqjmlcduwiwrsqj@tpwlb.com
Keywords: arithmetic,math,mathematics,python tutorial,libavi
Classifier: Development Status :: 1 - Planning
Classifier: Intended Audience :: Developers
Classifier: Programming Language :: Python :: 3
Classifier: Operating System :: Unix
Classifier: Operating System :: MacOS :: MacOS X
Classifier: Operating System :: Microsoft :: Windows
License-File: LICENSE.md
